{
  "card-Alas-Game": {
    "_info": {"group": "Game", "arg": "_info"},
    "Game_PackageName": {
      "task": "Alas",
      "group": "Game",
      "arg": "PackageName",
      "dt": "select",
      "value": "auto",
      "option": ["auto"]
    },
    "Game_ServerName": {
      "task": "Alas",
      "group": "Game",
      "arg": "ServerName",
      "dt": "select",
      "value": "disabled",
      "option": ["disabled"]
    }
  },
  "card-Alas-Emulator": {
    "_info": {"group": "Emulator", "arg": "_info"},
    "Emulator_Serial": {
      "task": "Device",
      "group": "Emulator",
      "arg": "Serial",
      "dt": "input",
      "value": "auto"
    },
    "Emulator_ScreenshotMethod": {
      "task": "Device",
      "group": "Emulator",
      "arg": "ScreenshotMethod",
      "dt": "select",
      "value": "auto",
      "option": ["auto", "ADB", "ADB_nc", "uiautomator2", "aScreenCap", "aScreenCap_nc", "DroidCast", "DroidCast_raw", "nemu_ipc", "ldopengl"]
    },
    "Emulator_ControlMethod": {
      "task": "Device",
      "group": "Emulator",
      "arg": "ControlMethod",
      "dt": "select",
      "value": "MaaTouch",
      "option": ["ADB", "uiautomator2", "minitouch", "Hermit", "MaaTouch"]
    },
    "Emulator_ScreenshotDedithering": {
      "task": "Device",
      "group": "Emulator",
      "arg": "ScreenshotDedithering",
      "dt": "checkbox",
      "value": false
    },
    "Emulator_AdbRestart": {
      "task": "Device",
      "group": "Emulator",
      "arg": "AdbRestart",
      "dt": "checkbox",
      "value": false
    }
  },
  "card-Alas-EmulatorInfo": {
    "_info": {"group": "EmulatorInfo", "arg": "_info"},
    "EmulatorInfo_Emulator": {
      "task": "Device",
      "group": "EmulatorInfo",
      "arg": "Emulator",
      "dt": "select",
      "value": "auto",
      "option": ["auto", "NoxPlayer", "NoxPlayer64", "BlueStacks4", "BlueStacks5", "BlueStacks4HyperV", "BlueStacks5HyperV", "LDPlayer3", "LDPlayer4", "LDPlayer9", "MuMuPlayer", "MuMuPlayerX", "MuMuPlayer12", "MEmuPlayer"]
    },
    "EmulatorInfo_Name": {
      "task": "Device",
      "group": "EmulatorInfo",
      "arg": "Name",
      "dt": "textarea",
      "value": "",
      "layout": "vert"
    },
    "EmulatorInfo_Path": {
      "task": "Device",
      "group": "EmulatorInfo",
      "arg": "Path",
      "dt": "textarea",
      "value": "",
      "layout": "vert"
    }
  },
  "card-Alas-Error": {
    "_info": {"group": "Error", "arg": "_info"},
    "Error_HandleError": {
      "task": "Device",
      "group": "Error",
      "arg": "HandleError",
      "dt": "checkbox",
      "value": true
    },
    "Error_SaveError": {
      "task": "Device",
      "group": "Error",
      "arg": "SaveError",
      "dt": "checkbox",
      "value": true
    },
    "Error_OnePushConfig": {
      "task": "Device",
      "group": "Error",
      "arg": "OnePushConfig",
      "dt": "textarea",
      "value": "provider: null",
      "layout": "vert"
    },
    "Error_ScreenshotLength": {
      "task": "Device",
      "group": "Error",
      "arg": "ScreenshotLength",
      "dt": "input-int",
      "value": 1
    }
  },
  "card-Alas-Optimization": {
    "_info": {"group": "Optimization", "arg": "_info"},
    "Optimization_ScreenshotInterval": {
      "task": "Device",
      "group": "Optimization",
      "arg": "ScreenshotInterval",
      "dt": "input-float",
      "value": 0.3
    },
    "Optimization_CombatScreenshotInterval": {
      "task": "Device",
      "group": "Optimization",
      "arg": "CombatScreenshotInterval",
      "dt": "input-float",
      "value": 1.0
    },
    "Optimization_TaskHoardingDuration": {
      "task": "Device",
      "group": "Optimization",
      "arg": "TaskHoardingDuration",
      "dt": "input-int",
      "value": 0
    },
    "Optimization_WhenTaskQueueEmpty": {
      "task": "Device",
      "group": "Optimization",
      "arg": "WhenTaskQueueEmpty",
      "dt": "select",
      "value": "goto_main",
      "option": ["stay_there", "goto_main", "close_game"]
    }
  },
  "card-RestartDeviceDisplay-RestartDevice": {
    "_info": {"group": "RestartDevice", "arg": "_info"},
    "Scheduler_Enable": {
      "task": "RestartDevice",
      "group": "Scheduler",
      "arg": "Enable",
      "cls": "SchedulerStatic",
      "dt": "select",
      "value": true,
      "option": [true]
    },
    "Scheduler_NextRun": {
      "task": "RestartDevice",
      "group": "Scheduler",
      "arg": "NextRun",
      "dt": "datetime",
      "value": "2020-01-01T00:00:00Z"
    },
    "Scheduler_ServerUpdate": {
      "task": "RestartDevice",
      "group": "Scheduler",
      "arg": "ServerUpdate",
      "dt": "input",
      "value": "00:00"
    }
  },
  "card-RestartGameDisplay-RestartGame": {
    "_info": {"group": "RestartGame", "arg": "_info"},
    "Scheduler_Enable": {
      "task": "RestartGame",
      "group": "Scheduler",
      "arg": "Enable",
      "cls": "SchedulerStatic",
      "dt": "select",
      "value": true,
      "option": [true]
    },
    "Scheduler_NextRun": {
      "task": "RestartGame",
      "group": "Scheduler",
      "arg": "NextRun",
      "dt": "datetime",
      "value": "2020-01-01T00:00:00Z"
    },
    "Scheduler_ServerUpdate": {
      "task": "RestartGame",
      "group": "Scheduler",
      "arg": "ServerUpdate",
      "dt": "input",
      "value": "00:00"
    }
  }
}