{
  "alas": {
    "_info": {
      "zh-CN": "alas",
      "en-US": "alas"
    },
    "card-Alas-Game": {
      "zh-CN": "Game",
      "en-US": "Game"
    },
    "card-Alas-Emulator": {
      "zh-CN": "模拟器设置",
      "en-US": "Emulator Settings"
    },
    "card-Alas-EmulatorInfo": {
      "zh-CN": "模拟器设置",
      "en-US": "Emulator Settings"
    },
    "card-Alas-Error": {
      "zh-CN": "调试设置",
      "en-US": "Debug Settings"
    },
    "card-Alas-Optimization": {
      "zh-CN": "优化设置",
      "en-US": "Optimization Settings"
    },
    "card-RestartDeviceDisplay-RestartDevice": {
      "zh-CN": "RestartDevice",
      "en-US": "RestartDevice"
    },
    "card-RestartGameDisplay-RestartGame": {
      "zh-CN": "RestartGame",
      "en-US": "RestartGame"
    }
  },
  "general": {
    "_info": {
      "zh-CN": "general",
      "en-US": "general"
    },
    "card-General-Retirement": {
      "zh-CN": "Retirement",
      "en-US": "Retirement"
    },
    "card-General-OneClickRetire": {
      "zh-CN": "OneClickRetire",
      "en-US": "OneClickRetire"
    },
    "card-General-Enhance": {
      "zh-CN": "Enhance",
      "en-US": "Enhance"
    },
    "card-General-OldRetire": {
      "zh-CN": "OldRetire",
      "en-US": "OldRetire"
    },
    "card-General-DropRecord": {
      "zh-CN": "DropRecord",
      "en-US": "DropRecord"
    }
  },
  "main": {
    "_info": {
      "zh-CN": "main",
      "en-US": "main"
    },
    "card-Main-Main": {
      "zh-CN": "主线图",
      "en-US": "Main"
    },
    "card-Main-Campaign": {
      "zh-CN": "Campaign",
      "en-US": "Campaign"
    },
    "card-Main-StopCondition": {
      "zh-CN": "StopCondition",
      "en-US": "StopCondition"
    },
    "card-Main-Fleet": {
      "zh-CN": "Fleet",
      "en-US": "Fleet"
    },
    "card-Main-Submarine": {
      "zh-CN": "Submarine",
      "en-US": "Submarine"
    },
    "card-Main-Emotion": {
      "zh-CN": "Emotion",
      "en-US": "Emotion"
    },
    "card-Main-HpControl": {
      "zh-CN": "HpControl",
      "en-US": "HpControl"
    },
    "card-Main-EnemyPriority": {
      "zh-CN": "EnemyPriority",
      "en-US": "EnemyPriority"
    }
  },
  "opsi": {
    "_info": {
      "zh-CN": "opsi",
      "en-US": "opsi"
    },
    "card-OpsiExplore-OpsiExplore": {
      "zh-CN": "OpsiExplore",
      "en-US": "OpsiExplore"
    },
    "card-OpsiDaily-OpsiDaily": {
      "zh-CN": "OpsiDaily",
      "en-US": "OpsiDaily"
    },
    "card-OpsiGeneral-OpsiGeneral": {
      "zh-CN": "大世界通用设置",
      "en-US": "OpsiGeneral"
    },
    "card-OpsiAshAssist-OpsiAshAssist": {
      "zh-CN": "META支援",
      "en-US": "Opsi AshAssist"
    }
  }
}